COPYING
MANIFEST.in
setup.cfg
setup.py
cspace/__init__.py
cspace/hgsite/__init__.py
cspace/hgsite/genshi.py
cspace/hgsite/meta.py
cspace/hgsite/site.py
cspace/hgsite/util.py
cspace_HgSite.egg-info/PKG-INFO
cspace_HgSite.egg-info/SOURCES.txt
cspace_HgSite.egg-info/dependency_links.txt
cspace_HgSite.egg-info/namespace_packages.txt
cspace_HgSite.egg-info/requires.txt
cspace_HgSite.egg-info/top_level.txt
cspace_HgSite.egg-info/zip-safe
examples/hello_world.html
site/common.html
site/error.html
site/index.html
site/site.html
site/res/common.css
site/res/common.js
site/res/jquery-license.txt
site/res/jquery.js
site/res/logo.ico
site/res/logo.png
site/res/logo128.png